README.md
setup.py
ADTLib/__init__.py
ADTLib.egg-info/PKG-INFO
ADTLib.egg-info/SOURCES.txt
ADTLib.egg-info/dependency_links.txt
ADTLib.egg-info/requires.txt
ADTLib.egg-info/top_level.txt
ADTLib/files/HihatADTLibAll.data-00000-of-00001
ADTLib/files/HihatADTLibAll.index
ADTLib/files/HihatADTLibAll.meta
ADTLib/files/KickADTLibAll.data-00000-of-00001
ADTLib/files/KickADTLibAll.index
ADTLib/files/KickADTLibAll.meta
ADTLib/files/PPParams.npy
ADTLib/files/SnareADTLibAll.data-00000-of-00001
ADTLib/files/SnareADTLibAll.index
ADTLib/files/SnareADTLibAll.meta
ADTLib/utils/__init__.py
bin/ADT