Metadata-Version: 1.1
Name: ADTLib
Version: 2.0.1
Summary: Automated Drum Trancription Library
Home-page: https://github.com/CarlSouthall/ADTLib
Author: Carl Southall
Author-email: carl.southall@bcu.ac.uk
License: BSD
Download-URL: https://github.com/CarlSouthall/ADTLib
Keywords: Drums,Transcription,Automated
Platform: UNKNOWN
Classifier: Programming Language :: Python :: 2.7
Classifier: License :: OSI Approved :: BSD License
Classifier: License :: Free for non-commercial use
Classifier: Topic :: Multimedia :: Sound/Audio :: Analysis
Classifier: Topic :: Scientific/Engineering :: Artificial Intelligence
